noterator/__init__.py
noterator/config.py
noterator/utils.py
noterator/plugins/__init__.py
noterator/plugins/desktop.py
noterator/plugins/email.py
noterator/plugins/hipchat.py
noterator/plugins/twilio.py
noterator-0.5.0.dist-info/AUTHORS.rst
noterator-0.5.0.dist-info/LICENSE
noterator-0.5.0.dist-info/METADATA
noterator-0.5.0.dist-info/WHEEL
noterator-0.5.0.dist-info/top_level.txt
noterator-0.5.0.dist-info/RECORD
