Metadata-Version: 2.1
Name: noterator
Version: 0.5.0
Summary: The Noterator: bringing notification to iteration.
Home-page: https://github.com/jimr/noterator
Author: James Rutherford
Author-email: jim@jimr.org
License: MIT license
Keywords: noterator
Platform: UNKNOWN
Classifier: Development Status :: 4 - Beta
Classifier: Intended Audience :: Developers
Classifier: License :: OSI Approved :: MIT License
Classifier: Natural Language :: English
Classifier: Programming Language :: Python :: 3
Classifier: Programming Language :: Python :: 3.5
Classifier: Programming Language :: Python :: 3.6
Classifier: Programming Language :: Python :: 3.7
Classifier: Programming Language :: Python :: 3.8
Requires-Dist: requests[security] (==2.20.0)
